var MCK_Umum={
"type": "FeatureCollection",
"name": "MCK_Umum",
"crs": { "type": "name", "properties": { "name": "urn:ogc:def:crs:OGC:1.3:CRS84" } },
"features": [
{ "type": "Feature", "properties": { "Id": 0 }, "geometry": { "type": "Point", "coordinates": [ 116.13754901191318, -8.627278300388536 ] } }
]
}
